<plist version="1.0">
  <dict>
    <key>PayloadContent</key>
    <array>
      <dict>
        <key>PayloadType</key>
        <string>com.apple.homeSync</string>
        <key>PayloadVersion</key>
        <integer>1</integer>
        <key>PayloadIdentifier</key>
        <string>com.apple.mdm.USCIS-MacManagement.local.4d8a18d0-a1c6-0133-40b9-185aebcee501.alacarte.mobility.e2e6aa80-a1ca-0133-40bd-185aebcee501.homeSync</string>
        <key>PayloadEnabled</key>
        <true />
        <key>PayloadUUID</key>
        <string>18db34bf-826c-8318-91f3-91bf37ea9b04</string>
        <key>PayloadDisplayName</key>
        <string>Mobility: Home Sync</string>
        <key>syncPreferencesAtLogin</key>
        <string>dontSync</string>
        <key>syncPreferencesAtLogout</key>
        <string>dontSync</string>
        <key>syncPreferencesAtSyncNow</key>
        <string>sync</string>
        <key>syncPreferencesInBackground</key>
        <string>dontSync</string>
        <key>replaceUserPrefSyncList</key>
        <true />
        <key>syncBackgroundSetAtLogin</key>
        <string>dontSync</string>
        <key>syncBackgroundSetAtLogout</key>
        <string>dontSync</string>
        <key>syncBackgroundSetAtSyncNow</key>
        <string>sync</string>
        <key>syncBackgroundSetInBackground</key>
        <string>dontSync</string>
        <key>replaceUserSyncList</key>
        <true />
        <key>periodicSyncOn</key>
        <false />
        <key>syncPeriodSeconds</key>
        <integer>300</integer>
        <key>syncedFolders-managed</key>
        <array>
          <dict>
            <key>path</key>
            <string>~</string>
          </dict>
        </array>
        <key>syncedPrefFolders-managed</key>
        <array>
          <dict>
            <key>path</key>
            <string>~/Library</string>
          </dict>
          <dict>
            <key>path</key>
            <string>~/Documents/Microsoft User Data</string>
          </dict>
        </array>
        <key>excludedItems-managed</key>
        <array>
          <dict>
            <key>value</key>
            <string>~/.SymAVQSFile</string>
            <key>comparison</key>
            <string>fullPath</string>
          </dict>
          <dict>
            <key>value</key>
            <string>~/Documents/Microsoft User Data</string>
            <key>comparison</key>
            <string>fullPath</string>
          </dict>
          <dict>
            <key>value</key>
            <string>~/Library</string>
            <key>comparison</key>
            <string>fullPath</string>
          </dict>
          <dict>
            <key>value</key>
            <string>~/NAVMac800QSFile</string>
            <key>comparison</key>
            <string>fullPath</string>
          </dict>
        </array>
        <key>excludedPrefItems-managed</key>
        <array>
          <dict>
            <key>value</key>
            <string>~/.SymAVQSFile</string>
            <key>comparison</key>
            <string>fullPath</string>
          </dict>
          <dict>
            <key>value</key>
            <string>~/Documents/Microsoft User Data/Entourage Temp</string>
            <key>comparison</key>
            <string>fullPath</string>
          </dict>
          <dict>
            <key>value</key>
            <string>~/Library/Application Support/SyncServices</string>
            <key>comparison</key>
            <string>fullPath</string>
          </dict>
          <dict>
            <key>value</key>
            <string>~/Library/Application Support/MobileSync</string>
            <key>comparison</key>
            <string>fullPath</string>
          </dict>
          <dict>
            <key>value</key>
            <string>~/Library/Caches</string>
            <key>comparison</key>
            <string>fullPath</string>
          </dict>
          <dict>
            <key>value</key>
            <string>~/Library/Calendars/Calendar Cache</string>
            <key>comparison</key>
            <string>fullPath</string>
          </dict>
          <dict>
            <key>value</key>
            <string>~/Library/Logs</string>
            <key>comparison</key>
            <string>fullPath</string>
          </dict>
          <dict>
            <key>value</key>
            <string>~/Library/Mail/AvailableFeeds</string>
            <key>comparison</key>
            <string>fullPath</string>
          </dict>
          <dict>
            <key>value</key>
            <string>~/Library/Mail/Envelope Index</string>
            <key>comparison</key>
            <string>fullPath</string>
          </dict>
          <dict>
            <key>value</key>
            <string>~/Library/Preferences/Macromedia/Flash Player</string>
            <key>comparison</key>
            <string>fullPath</string>
          </dict>
          <dict>
            <key>value</key>
            <string>~/Library/Printers</string>
            <key>comparison</key>
            <string>fullPath</string>
          </dict>
          <dict>
            <key>value</key>
            <string>~/Library/PubSub/Database</string>
            <key>comparison</key>
            <string>fullPath</string>
          </dict>
          <dict>
            <key>value</key>
            <string>~/Library/PubSub/Downloads</string>
            <key>comparison</key>
            <string>fullPath</string>
          </dict>
          <dict>
            <key>value</key>
            <string>~/Library/PubSub/Feeds</string>
            <key>comparison</key>
            <string>fullPath</string>
          </dict>
          <dict>
            <key>value</key>
            <string>~/Library/Safari/Icons.db</string>
            <key>comparison</key>
            <string>fullPath</string>
          </dict>
          <dict>
            <key>value</key>
            <string>~/Library/Safari/HistoryIndex.sk</string>
            <key>comparison</key>
            <string>fullPath</string>
          </dict>
          <dict>
            <key>value</key>
            <string>~/Library/iTunes/iPhone Software Updates</string>
            <key>comparison</key>
            <string>fullPath</string>
          </dict>
          <dict>
            <key>value</key>
            <string>IMAP-</string>
            <key>comparison</key>
            <string>startsWith</string>
          </dict>
          <dict>
            <key>value</key>
            <string>Exchange-</string>
            <key>comparison</key>
            <string>startsWith</string>
          </dict>
          <dict>
            <key>value</key>
            <string>EWS-</string>
            <key>comparison</key>
            <string>startsWith</string>
          </dict>
          <dict>
            <key>value</key>
            <string>Mac-</string>
            <key>comparison</key>
            <string>startsWith</string>
          </dict>
        </array>
      </dict>
    </array>
    <key>PayloadDescription</key>
    <string></string>
    <key>PayloadDisplayName</key>
    <string>MacOS - Mobility Settings and Folder Configurations/V_1</string>
    <key>PayloadIdentifier</key>
    <string>80c69311-8af0-4b58-9f75-78d83b109640</string>
    <key>PayloadOrganization</key>
    <string></string>
    <key>PayloadRemovalDisallowed</key>
    <false />
    <key>PayloadType</key>
    <string>Configuration</string>
    <key>PayloadUUID</key>
    <string>312eeede-e33d-4d9d-b610-268eaa619006</string>
    <key>PayloadVersion</key>
    <integer>1</integer>
    <key>PayloadScope</key>
    <string>Device</string>
  </dict>
</plist>